Workbook

Sheet Assumptions
B1: OVERWATER VILLA FLEET — REV. 4
B2: All blue cells are inputs — change them to run scenarios
B4: 1A. THE ASSET
B5: Retail MSRP | C5: 1250000
B6: Dealer discount (%) | C6: 0.35
B7: Dealer cost per boat | C7: =C5*(1-C6) -> 812500
B8: Total boats | C8: 6
B9: Revenue boats | C9: 5
B10: Crew/HQ boats | C10: 1
B11: LOA for slip billing (ft) | C11: 50
B13: 1B. FINANCING
B14: Down payment % | C14: 0.25
B15: Interest rate (annual) | C15: 0.07
B16: Amortization (years) | C16: 20
B17: Monthly rate | C17: =C15/12 -> 0.0058333333
B18: Periods (months) | C18: =C16*12 -> 240
B19: Fleet dealer cost | C19: =C7*C8 -> 4875000
B20: Cash equity (down payment) | C20: =C19*C14 -> 1218750
B21: Loan principal | C21: =C19*(1-C14) -> 3656250
B22: Monthly payment | C22: =-PMT(C17,C18,C21) -> 28346.867
B23: Annual debt service | C23: =C22*12 -> 340162.41
B25: 1C. OPERATIONAL CALENDAR
B26: Calendar year (days) | C26: 365
B27: Southbound migration (days) | C27: 24
B28: Northbound sprint (days) | C28: 6
B29: Total migration downtime | C29: =C27+C28 -> 30
B30: Active port days | C30: =C26-C29 -> 335
B31: Active excursion weeks | C31: 48
B33: 1D. JV RATES & SPLITS
B34: Villa nightly rate floor | C34: 2000
B35: Excursion day rate | C35: 2000
B36: Hotel commission — villas | C36: 0.225
B37: Hotel commission — excursions | C37: 0.2
B39: 1E. OCCUPANCY & UTILIZATION
B40: Villa occupancy rate | C40: 0.35
B41: Nights per boat per year | C41: =INT(C30*C40) -> 117
B42: Hotel excursions/boat/week | C42: 1
B43: Hotel excursions/boat/year | C43: =C42*C31 -> 48
B44: Operator calendar bump | C44: 0.2
B45: Operator excursions/boat/year | C45: =INT(C30*C44) -> 67
B46: Excursion duration (hours) | C46: 3
B48: 1F. STAFFING
B49: Captains | C49: 2
B50: Captain salary each | C50: 70000
B51: Stewards | C51: 2
B52: Steward salary each | C52: 60000
B53: Total crew payroll | C53: =C49*C50+C51*C52 -> 260000
B55: 1G. HOUSEKEEPING
B56: Cost per villa night (to hotel) | C56: 50
B57: Hotel actual laundry cost/night | C57: 15
B59: 1H. INSURANCE & MAINTENANCE
B60: Budget per boat per year | C60: 20000
B61: P&I umbrella | C61: 10000000
B63: 1I. FUEL & CONSUMABLES
B64: Annual fuel budget | C64: 130000
B66: 1J. CONVOY SPRINT
B67: Freelance captains | C67: 8
B68: Daily rate | C68: 350
B69: Duration (days) | C69: 6
B70: Flights | C70: 4000
B71: Total convoy cost | C71: =C67*C68*C69+C70 -> 20800
B73: 1K. EXIT / LIQUIDATION
B74: Exit timing (months) | C74: 36
B75: Conservative residual (% MSRP) | C75: 0.5
B76: Upside residual (% MSRP) | C76: 0.6
B78: 1L. CRISIS YEAR
B79: Crisis villa occupancy | C79: 0.2
B80: Crisis baseline excursions (fleet) | C80: 200
B81: Crisis operator bump | C81: 0.1
B83: 1M. HOTEL BASELINE
B84: Transient rate ($/ft/night) | C84: 6
B85: Transient occupancy | C85: 0.5
B87: 1N. HOTEL ANCILLARY
B88: Villa guest F&B/spa ($/night) | C88: 200
B89: Excursion guest ($/excursion) | C89: 75

Sheet Operator Financials
B1: OWNER/OPERATOR — DETAILED FINANCIAL MODEL
B3: CAPITAL STRUCTURE
B4: MSRP per boat | C4: =Assumptions!C5 -> 1250000
B5: Dealer cost per boat | C5: =Assumptions!C7 -> 812500
B6: Fleet dealer cost (6 boats) | C6: =Assumptions!C19 -> 4875000
B7: Fleet retail value | C7: =Assumptions!C5*Assumptions!C8 -> 7500000
B8: Day-1 equity cushion | C8: =C7-C6 -> 2625000
B9: Cash equity (25%) | C9: =Assumptions!C20 -> 1218750
B10: Loan principal (75%) | C10: =Assumptions!C21 -> 3656250
B11: Monthly payment | C11: =Assumptions!C22 -> 28346.867
B12: Annual debt service | C12: =Assumptions!C23 -> 340162.41
B14: STREAM A: VILLA NIGHTS
B15: Active port days | C15: =Assumptions!C30 -> 335
B16: Villa occupancy | C16: =Assumptions!C40 -> 0.35
B17: Nights per boat | C17: =INT(C15*C16) -> 117
B18: Revenue boats | C18: =Assumptions!C9 -> 5
B19: Total fleet villa nights | C19: =C17*C18 -> 585
B20: Nightly rate | C20: =Assumptions!C34 -> 2000
B21: GROSS VILLA REVENUE | C21: =C19*C20 -> 1170000
B22: Hotel cut (22.5%) | C22: =C21*Assumptions!C36 -> 263250
B23: OPERATOR VILLA SHARE (77.5%) | C23: =C21-C22 -> 906750
B25: STREAM B: HOTEL EXCURSIONS
B26: Excursions/boat/year | C26: =Assumptions!C43 -> 48
B27: Total fleet excursions | C27: =C26*Assumptions!C9 -> 240
B28: Rate/excursion | C28: =Assumptions!C35 -> 2000
B29: GROSS EXCURSION REVENUE | C29: =C27*C28 -> 480000
B30: Hotel cut (20%) | C30: =C29*Assumptions!C37 -> 96000
B31: OPERATOR EXCURSION SHARE (80%) | C31: =C29-C30 -> 384000
B33: STREAM C: OPERATOR EXCURSIONS (+20%)
B34: Extra excursions/boat/year | C34: =Assumptions!C45 -> 67
B35: Total fleet extra excursions | C35: =C34*Assumptions!C9 -> 335
B36: Rate/excursion | C36: =Assumptions!C35 -> 2000
B37: GROSS EXTRA REVENUE | C37: =C35*C36 -> 670000
B38: Hotel cut (20%) | C38: =C37*Assumptions!C37 -> 134000
B39: OPERATOR EXTRA SHARE (80%) | C39: =C37-C38 -> 536000
B41: REVENUE TOTALS
B42: Total gross revenue | C42: =C21+C29+C37 -> 2320000
B43: Total hotel intake | C43: =C22+C30+C38 -> 493250
B44: OPERATOR GROSS SHARE | C44: =C23+C31+C39 -> 1826750
B46: OPERATING EXPENSES
B47: Crew payroll | C47: =Assumptions!C53 -> 260000
B48: Convoy sprint | C48: =Assumptions!C71 -> 20800
B49: Laundry & amenities | C49: =C19*Assumptions!C56 -> 29250
B50: Insurance & maintenance | C50: =Assumptions!C60*Assumptions!C8 -> 120000
B51: Fuel & consumables | C51: =Assumptions!C64 -> 130000
B52: TOTAL OPEX | C52: =SUM(C47:C51) -> 560050
B54: ANNUAL P&L
B55: Operator gross share | C55: =C44 -> 1826750
B56: Less: Total OpEx | C56: =-C52 -> -560050
B57: NOI | C57: =C55+C56 -> 1266700
B58: Less: Debt service | C58: =-C12 -> -340162.41
B59: NET CASH FLOW | C59: =C57+C58 -> 926537.59
B61: Cash-on-Cash ROI | C61: =C59/C9 -> 0.76023597
B62: Equity Payback (months) | C62: =C9/C59*12 -> 15.784573
B64: 3-YEAR LIFECYCLE
B65: CRISIS YEAR (Year 2):
B66: Crisis villa nights (fleet) | C66: =Assumptions!C9*INT(Assumptions!C30*Assumptions!C79) -> 335
B67: Crisis villa op share | C67: =C66*Assumptions!C34*(1-Assumptions!C36) -> 519250
B68: Crisis base excursions | C68: =Assumptions!C80 -> 200
B69: Crisis base ex op share | C69: =C68*Assumptions!C35*(1-Assumptions!C37) -> 320000
B70: Crisis extra excursions | C70: =Assumptions!C9*INT(Assumptions!C30*Assumptions!C81) -> 165
B71: Crisis extra ex op share | C71: =C70*Assumptions!C35*(1-Assumptions!C37) -> 264000
B72: Crisis op share total | C72: =C67+C69+C71 -> 1103250
B73: Crisis OpEx | C73: =Assumptions!C53+Assumptions!C71+C66*Assumptions!C56+Assumptions!C60*Assumptions!C8+Assumptions!C64 -> 547550
B74: Crisis NOI | C74: =C72-C73 -> 555700
B75: CRISIS NET CASH FLOW | C75: =C74-C12 -> 215537.59
B77: TIMELINE:
B78: Initial equity | C78: =-C9 -> -1218750
B79: Year 1 — Optimized | C79: =C59 -> 926537.59
B80: Year 2 — Perfect Storm | C80: =C75 -> 215537.59
B81: Year 3 — Recovery | C81: =C59 -> 926537.59
B82: Cumulative operating cash | C82: =C79+C80+C81 -> 2068612.8
B84: EXIT:
B85: Loan balance @36 months | C85: =FV(Assumptions!C17,Assumptions!C74,-C11,C10) -> -3375990.9
B86: Principal paid down | C86: =C10+C85 -> 280259.09
B87: Interest paid (36 months) | C87: =C11*36-C86 -> 740228.14
B88: Fleet sale (50% MSRP) | C88: =Assumptions!C8*Assumptions!C5*Assumptions!C75 -> 3750000
B89: Exit surplus | C89: =C88+C85 -> 374009.09
B91: SETTLEMENT:
B92: Total cash extracted | C92: =C82+C89 -> 2442621.9
B93: Less: Initial equity | C93: =-C9 -> -1218750
B94: NET LIFECYCLE PROFIT | C94: =C92+C93 -> 1223871.9
B96: 3-Year ROE | C96: =C94/C9 -> 1.0042026
B97: Annualized ROI | C97: =C96/3 -> 0.33473419
B99: UPSIDE — 60% MSRP, NO CRISIS
B100: Cumulative cash (no crisis) | C100: =C59*3 -> 2779612.8
B101: Fleet sale (60% MSRP) | C101: =Assumptions!C8*Assumptions!C5*Assumptions!C76 -> 4500000
B102: Exit surplus | C102: =C101+C85 -> 1124009.1
B103: NET LIFECYCLE PROFIT (upside) | C103: =C100+C102-C9 -> 2684871.9
B104: 3-Year ROE (upside) | C104: =C103/C9 -> 2.2029718

Sheet Hotel Financials
B1: HOTEL / MARINA — DETAILED FINANCIALS
B3: BASELINE — TRANSIENT DOCKAGE
B4: Number of slips | C4: =Assumptions!C8 -> 6
B5: LOA for billing (ft) | C5: =Assumptions!C11 -> 50
B6: Transient rate ($/ft/night) | C6: =Assumptions!C84 -> 6
B7: Transient occupancy | C7: =Assumptions!C85 -> 0.5
B8: Billable nights | C8: =INT(Assumptions!C30*C7) -> 167
B9: Revenue per slip per night | C9: =C5*C6 -> 300
B10: Revenue per slip per year | C10: =C9*C8 -> 50100
B11: TOTAL TRANSIENT BASELINE | C11: =C10*C4 -> 300600
B13: JV INCOME BREAKDOWN
B14: Villa commission (22.5%) | C14: ='Operator Financials'!C22 -> 263250
B15: Base excursion commission (20%) | C15: ='Operator Financials'!C30 -> 96000
B16: Operator excursion commission (20%) | C16: ='Operator Financials'!C38 -> 134000
B17: Total commission income | C17: =C14+C15+C16 -> 493250
B19: Laundry fees from operator | C19: ='Operator Financials'!C49 -> 29250
B20: Hotel laundry cost | C20: =-'Operator Financials'!C19*Assumptions!C57 -> -8775
B21: Admin/PMS integration | C21: -12000
B23: HOTEL NET JV PROFIT | C23: =C17+C19+C20+C21 -> 501725
B25: ANCILLARY REVENUE (ESTIMATED)
B26: Villa F&B/spa spend | C26: ='Operator Financials'!C19*Assumptions!C88 -> 117000
B27: Excursion guest spend | C27: =('Operator Financials'!C27+'Operator Financials'!C35)*Assumptions!C89 -> 43125
B28: Total ancillary | C28: =C26+C27 -> 160125
B30: TOTAL HOTEL ECONOMIC BENEFIT | C30: =C23+C28 -> 661850
B32: HEAD-TO-HEAD COMPARISON
C33: Transient | D33: JV Model
B34: Net annual to hotel | C34: =C11 -> 300600 | D34: =C23 -> 501725
B35: Yield per linear foot | C35: =C11/(C4*C5) -> 1002 | D35: =C23/(C4*C5) -> 1672.4167
B36: Total with ancillary | C36: =C11 -> 300600 | D36: =C30 -> 661850
B38: Uplift — JV profit only | C38: =(C23-C11)/C11 -> 0.66907851
B39: Uplift — with ancillary | C39: =(C30-C11)/C11 -> 1.2017631
B40: Quarterly uplift ($) | C40: =(C23-C11)/4 -> 50281.25

Sheet Sensitivity
B1: SENSITIVITY — ANNUAL NET CASH FLOW
B2: After all OpEx + debt service; excursion revenue held constant
B4: Villa Rate | C4: 50% Occ | D4: 35% Occ | E4: 25% Occ | F4: 15% Occ
B5: $3,000/nt | C5: 1948663 | D5: 1379913 | E5: 993163 | F5: 617788
B6: $2,500/nt | C6: 1625100 | D6: 1153225 | E6: 832350 | F6: 520913
B7: $2,000/nt | C7: 1301538 | D7: 926538 | E7: 671538 | F7: 424038
B8: $1,500/nt | C8: 977975 | D8: 699850 | E8: 510725 | F8: 327163
B9: $1,000/nt | C9: 654413 | D9: 473163 | E9: 349913 | F9: 230288
B11: ★ Teal = base case ($2,000/night at 35% occ)
B12: Cash-positive across every scenario
